async_negotiate_sspi/__init__.py
async_negotiate_sspi/__version__.py
async_negotiate_sspi/negotiate.py
async_negotiate_sspi/negotiate_ws.py
async_negotiate_sspi/py.typed
async_negotiate_sspi-0.1.4.dist-info/LICENSE.md
async_negotiate_sspi-0.1.4.dist-info/METADATA
async_negotiate_sspi-0.1.4.dist-info/WHEEL
async_negotiate_sspi-0.1.4.dist-info/top_level.txt
async_negotiate_sspi-0.1.4.dist-info/RECORD
