Metadata-Version: 2.1
Name: async-negotiate-sspi
Version: 0.1.4
Summary: Single-Sign On for HTTP and Websocket Negotiate authentication in async frameworks on Windows
Home-page: https://github.com/newvicx/async_negotiate_sspi
Author: Chris Newville
Author-email: chrisnewville1396@gmail.com
License: MIT
Project-URL: Changelog, https://github.com/newvicx/async_negotiate_sspi/blob/master/CHANGELOG.md
Project-URL: Source, https://github.com/newvicx/async_negotiate_sspi
Platform: UNKNOWN
Classifier: Development Status :: 4 - Beta
Classifier: Environment :: Web Environment
Classifier: Intended Audience :: Developers
Classifier: License :: OSI Approved :: MIT License
Classifier: Operating System :: Microsoft :: Windows
Classifier: Topic :: Internet :: WWW/HTTP
Classifier: Framework :: AsyncIO
Classifier: Framework :: Trio
Classifier: Programming Language :: Python :: 3
Classifier: Programming Language :: Python :: 3.7
Classifier: Programming Language :: Python :: 3.8
Classifier: Programming Language :: Python :: 3.9
Classifier: Programming Language :: Python :: 3.10
Classifier: Programming Language :: Python :: 3 :: Only
Requires-Python: >=3.7
License-File: LICENSE.md
Requires-Dist: httpx-extensions (>=0.1.1)
Requires-Dist: pywin32 (>=303)
Requires-Dist: ws-auth (>=0.1.0)
